openazharmony/__init__.py
openazharmony/client.py
openazharmony/contracts.py
openazharmony/docs/AZURE.md
openazharmony/docs/CHANGELOG.md
openazharmony/docs/EXAMPLES.md
openazharmony/docs/FAQ.md
openazharmony/docs/INSTALL.md
openazharmony/docs/LIMITATIONS.md
openazharmony/docs/PYTHON.md
openazharmony/docs/README.md
openazharmony/docs/RESPONSE_FORMATS.md
openazharmony/docs/SECURITY.md
openazharmony/docs/TROUBLESHOOTING.md
openazharmony/docs/__init__.py
openazharmony/docs/__main__.py
openazharmony-0.0.0.dist-info/licenses/LICENSE
openazharmony-0.0.0.dist-info/METADATA
openazharmony-0.0.0.dist-info/WHEEL
openazharmony-0.0.0.dist-info/top_level.txt
openazharmony-0.0.0.dist-info/RECORD
