Metadata-Version: 2.4
Name: openazharmony
Version: 0.0.0
Summary: OpenAI and Azure compatibility helpers with response format contracts.
Author-email: Brent Carpenetti <brentcarpenetti@gmail.com>
License-Expression: MIT
Requires-Python: >=3.10
License-File: LICENSE
Requires-Dist: openai>=1.0
Requires-Dist: pydantic>=2.0
Dynamic: license-file
